<mxGraphModel dx="939" dy="466" grid="1" gridSize="10" guides="1" tooltips="1" connect="1" arrows="1" fold="1" page="1" pageScale="1" pageWidth="850" pageHeight="1100"><root><mxCell id="0"/><mxCell id="1" parent="0"/><mxCell id="4" value="" style="edgeStyle=orthogonalEdgeStyle;rounded=0;html=1;jettySize=auto;orthogonalLoop=1;" edge="1" parent="1" source="2" target="3"><mxGeometry relative="1" as="geometry"/></mxCell><mxCell id="2" value="Client" style="ellipse;whiteSpace=wrap;html=1;" vertex="1" parent="1"><mxGeometry x="360" y="110" width="90" height="70" as="geometry"/></mxCell><mxCell id="3" value="Svr" style="ellipse;whiteSpace=wrap;html=1;" vertex="1" parent="1"><mxGeometry x="360" y="225" width="90" height="70" as="geometry"/></mxCell><mxCell id="5" value="命令请求" style="text;html=1;resizable=0;points=[];autosize=1;align=left;verticalAlign=top;spacingTop=-4;" vertex="1" parent="1"><mxGeometry x="410" y="197" width="60" height="20" as="geometry"/></mxCell><mxCell id="6" value="现有AOF文件" style="rounded=0;whiteSpace=wrap;html=1;" vertex="1" parent="1"><mxGeometry x="240" y="353" width="120" height="60" as="geometry"/></mxCell><mxCell id="9" value="" style="endArrow=classic;html=1;entryX=0.5;entryY=0;exitX=0;exitY=1;" edge="1" parent="1" source="3" target="6"><mxGeometry width="50" height="50" relative="1" as="geometry"><mxPoint x="230" y="480" as="sourcePoint"/><mxPoint x="280" y="430" as="targetPoint"/></mxGeometry></mxCell><mxCell id="10" value="重写AOF缓存&lt;br&gt;" style="rounded=0;whiteSpace=wrap;html=1;" vertex="1" parent="1"><mxGeometry x="450" y="353" width="120" height="60" as="geometry"/></mxCell><mxCell id="11" value="" style="endArrow=classic;html=1;entryX=0.5;entryY=0;exitX=1;exitY=1;" edge="1" target="10" parent="1" source="3"><mxGeometry width="50" height="50" relative="1" as="geometry"><mxPoint x="592.7241379310344" y="287.344827586207" as="sourcePoint"/><mxPoint x="500" y="433" as="targetPoint"/></mxGeometry></mxCell><mxCell id="13" value="命令协议内容" style="text;html=1;resizable=0;points=[];autosize=1;align=left;verticalAlign=top;spacingTop=-4;" vertex="1" parent="1"><mxGeometry x="360" y="300" width="90" height="20" as="geometry"/></mxCell></root></mxGraphModel>